ValuesConverterProgram.py
valuesconverterprogram-1.0.0.dist-info/WHEEL
valuesconverterprogram-1.0.0.dist-info/METADATA
valuesconverterprogram-1.0.0.dist-info/RECORD
